{
  "original_idea": {
    "title": "Create an AI-powered code review system that automatically detects bugs and suggests improvements",
    "description": "Create an AI-powered code review system that automatically detects bugs and suggests improvements",
    "content": "Create an AI-powered code review system that automatically detects bugs and suggests improvements",
    "source": "user_input",
    "author": "user",
    "context": "user_suggestion",
    "timestamp": "2025-10-25T09:29:26.352Z"
  },
  "evolution_history": [],
  "current_state": "captured",
  "future_potential": []
}